django_task_worker/__init__.py
django_task_worker/admin.py
django_task_worker/apps.py
django_task_worker/client.py
django_task_worker/logger.py
django_task_worker/models.py
django_task_worker/tests.py
django_task_worker/worker.py
django_task_worker/management/commands/run_worker.py
django_task_worker/migrations/0001_initial.py
django_task_worker/migrations/0002_databasetask_next_attempt_at.py
django_task_worker/migrations/__init__.py
django_task_worker/tasks/example_tasks.py
django_task_worker-0.0.7.dist-info/licenses/LICENSE
django_task_worker-0.0.7.dist-info/METADATA
django_task_worker-0.0.7.dist-info/WHEEL
django_task_worker-0.0.7.dist-info/entry_points.txt
django_task_worker-0.0.7.dist-info/top_level.txt
django_task_worker-0.0.7.dist-info/RECORD
