Metadata-Version: 2.4
Name: django-task-worker
Version: 0.0.7
Summary: Task worker for Django using Redis and a database queue
Author-email: Yoongi Kim <yoongi@yoongi.kim>
Maintainer-email: Yoongi Kim <yoongi@yoongi.kim>
License: Apache License 2.0
Project-URL: Homepage, https://github.com/YoongiKim/django-task-worker
Project-URL: Repository, https://github.com/YoongiKim/django-task-worker
Project-URL: Bug Tracker, https://github.com/YoongiKim/django-task-worker/issues
Keywords: django,task,async,worker,queue,redis
Classifier: Development Status :: 4 - Beta
Classifier: Framework :: Django
Classifier: Programming Language :: Python :: 3
Classifier: Programming Language :: Python :: 3.6
Classifier: Programming Language :: Python :: 3.7
Classifier: Programming Language :: Python :: 3.8
Classifier: Programming Language :: Python :: 3.9
Classifier: Programming Language :: Python :: 3.10
Classifier: Programming Language :: Python :: 3.11
Classifier: Programming Language :: Python :: 3.12
Classifier: License :: OSI Approved :: Apache Software License
Classifier: Operating System :: OS Independent
Requires-Python: >=3.6
License-File: LICENSE
Requires-Dist: django>=3.2
Requires-Dist: redis>=4.5.0
Requires-Dist: shortuuid>=1.0.11
Requires-Dist: stopit>=1.1.2
Requires-Dist: setuptools>=65.5.1
Provides-Extra: postgres
Requires-Dist: psycopg2-binary>=2.9.0; extra == "postgres"
Provides-Extra: dev
Requires-Dist: pytest>=7.0.0; extra == "dev"
Requires-Dist: pytest-django>=4.5.2; extra == "dev"
Dynamic: license-file
